daqpp/__init__.py
daqpp/daq.py
daqpp/soap.py
daqpp-2.0.3.dist-info/METADATA
daqpp-2.0.3.dist-info/WHEEL
daqpp-2.0.3.dist-info/top_level.txt
daqpp-2.0.3.dist-info/RECORD
