Metadata-Version: 2.1
Name: daqpp
Version: 2.0.3
Summary: Communication with daqpp via soap..
Author-email: Carlos Lacasta <carlos.lacasta@alibavasystems.com>
Project-URL: Homepage, https://igit.ific.uv.es
Project-URL: Bug Tracker, https://igit.ific.uv.es
Classifier: Programming Language :: Python :: 3
Classifier: Operating System :: OS Independent
Requires-Python: >=3.7
Requires-Dist: zeep (>=2.5.0)
